odoo/addons/odoo_repository/README.rst
odoo/addons/odoo_repository/__init__.py
odoo/addons/odoo_repository/__manifest__.py
odoo/addons/odoo_repository/controllers/__init__.py
odoo/addons/odoo_repository/controllers/main.py
odoo/addons/odoo_repository/data/ir_cron.xml
odoo/addons/odoo_repository/data/odoo.repository.csv
odoo/addons/odoo_repository/data/odoo_branch.xml
odoo/addons/odoo_repository/data/odoo_module.xml
odoo/addons/odoo_repository/data/odoo_repository.xml
odoo/addons/odoo_repository/data/odoo_repository_addons_path.xml
odoo/addons/odoo_repository/data/odoo_repository_org.xml
odoo/addons/odoo_repository/data/queue_job.xml
odoo/addons/odoo_repository/lib/__init__.py
odoo/addons/odoo_repository/lib/scanner.py
odoo/addons/odoo_repository/migrations/16.0.1.1.0/post-migration.py
odoo/addons/odoo_repository/migrations/16.0.1.2.0/pre-migration.py
odoo/addons/odoo_repository/migrations/16.0.1.3.0/post-migration.py
odoo/addons/odoo_repository/migrations/16.0.1.3.1/post-migration.py
odoo/addons/odoo_repository/migrations/16.0.1.4.1/pre-migration.py
odoo/addons/odoo_repository/models/__init__.py
odoo/addons/odoo_repository/models/authentication_token.py
odoo/addons/odoo_repository/models/odoo_author.py
odoo/addons/odoo_repository/models/odoo_branch.py
odoo/addons/odoo_repository/models/odoo_license.py
odoo/addons/odoo_repository/models/odoo_maintainer.py
odoo/addons/odoo_repository/models/odoo_module.py
odoo/addons/odoo_repository/models/odoo_module_branch.py
odoo/addons/odoo_repository/models/odoo_module_branch_version.py
odoo/addons/odoo_repository/models/odoo_module_category.py
odoo/addons/odoo_repository/models/odoo_module_dev_status.py
odoo/addons/odoo_repository/models/odoo_python_dependency.py
odoo/addons/odoo_repository/models/odoo_repository.py
odoo/addons/odoo_repository/models/odoo_repository_addons_path.py
odoo/addons/odoo_repository/models/odoo_repository_branch.py
odoo/addons/odoo_repository/models/odoo_repository_org.py
odoo_addon_odoo_repository-16.0.1.4.4.dist-info/METADATA
odoo_addon_odoo_repository-16.0.1.4.4.dist-info/WHEEL
odoo_addon_odoo_repository-16.0.1.4.4.dist-info/top_level.txt
odoo_addon_odoo_repository-16.0.1.4.4.dist-info/RECORD
