Metadata-Version: 2.1
Name: odoo-addon-odoo_repository
Version: 16.0.1.4.4
Summary: Base module to host data collected from Odoo repositories.
Home-page: https://github.com/OCA/module-composition-analysis
Author: Camptocamp, Odoo Community Association (OCA)
Author-email: support@odoo-community.org
License: AGPL-3
Classifier: Programming Language :: Python
Classifier: Framework :: Odoo
Classifier: Framework :: Odoo :: 16.0
Classifier: License :: OSI Approved :: GNU Affero General Public License v3
Requires-Python: >=3.10
Requires-Dist: gitpython
Requires-Dist: odoo-addon-base-time-window<16.1dev,>=16.0dev
Requires-Dist: odoo-addon-queue-job<16.1dev,>=16.0dev
Requires-Dist: odoo-addons-parser
Requires-Dist: odoo<16.1dev,>=16.0a
